gdec/__init__.py
gdec/eld.py
gdec/gid.py
gdec/glmnet.py
gdec/gpgid.py
gdec/gppid.py
gdec/gpreg.py
gdec/jaxgp.py
gdec/npgp.py
gdec/pid.py
gdec/snd.py
gdec/synthetic.py
gdec/torchgp.py
gdec/useful.py
gdec/utils.py
gdec/vgpmd.py
gdec-0.0.10.dist-info/LICENSE.txt
gdec-0.0.10.dist-info/METADATA
gdec-0.0.10.dist-info/WHEEL
gdec-0.0.10.dist-info/top_level.txt
gdec-0.0.10.dist-info/RECORD
